cht_bathymetry/__init__.py
cht_bathymetry/bathymetry_database.py
cht_bathymetry/tiling.py
cht_bathymetry/tiling_example.py
cht_bathymetry/tiling_example_gebco22.py
cht_bathymetry/utils.py
cht_bathymetry-1.0.0.dist-info/LICENSE
cht_bathymetry-1.0.0.dist-info/METADATA
cht_bathymetry-1.0.0.dist-info/WHEEL
cht_bathymetry-1.0.0.dist-info/top_level.txt
cht_bathymetry-1.0.0.dist-info/RECORD
